[{"title":"belarusiaga ruble","code":"BYN","symbol":"Br","position":0},{"title":"mɔritaniaga ouguiya","code":"MRU","symbol":"UM","position":0},{"title":"sierra leonega leone","code":"SLE","symbol":"Le","position":0},{"title":"são tomé kple príncipega dobra","code":"STN","symbol":"Db","position":0},{"title":"venezuelaga bolívar","code":"VES","symbol":"Bs.S","position":0},{"title":"Zimbabwean Gold","code":"ZWG","symbol":"ZiG","position":0},{"title":"afghanistanga afghani","code":"AFN","symbol":"؋","position":0},{"title":"aiselandga króna","code":"ISK","symbol":"kr","position":0},{"title":"albaniaga lek","code":"ALL","symbol":"Lek","position":0},{"title":"aldzeriaga dinar","code":"DZD","symbol":"","position":0},{"title":"angolaga kwanza","code":"AOA","symbol":"","position":0},{"title":"anyiehe afrikaga rand","code":"ZAR","symbol":"R","position":0},{"title":"anyiehe koreaga won","code":"KRW","symbol":"₩","position":0},{"title":"argentinaga peso","code":"ARS","symbol":"$","position":0},{"title":"armeniaga dram","code":"AMD","symbol":"","position":0},{"title":"arubaga lorin","code":"AWG","symbol":"ƒ","position":0},{"title":"australiaga dollar","code":"AUD","symbol":"$","position":0},{"title":"azerbaidzanga manat","code":"AZN","symbol":"ман","position":0},{"title":"bahamiaga dollar","code":"BSD","symbol":"$","position":0},{"title":"bahrainga dinar","code":"BHD","symbol":"","position":0},{"title":"bangladeshga taka","code":"BDT","symbol":"","position":0},{"title":"barbadiaga dollar","code":"BBD","symbol":"$","position":0},{"title":"belizega dollar","code":"BZD","symbol":"BZ$","position":0},{"title":"bermudaga dollar","code":"BMD","symbol":"$","position":0},{"title":"bhutanga ngultrum","code":"BTN","symbol":"","position":0},{"title":"boliviaga boliviano","code":"BOB","symbol":"$b","position":0},{"title":"boliviaga mvdol","code":"BOV","symbol":"","position":0},{"title":"bosnia-herzegovinaga convertible mark","code":"BAM","symbol":"KM","position":0},{"title":"botswanaga pula","code":"BWP","symbol":"P","position":0},{"title":"brazilga real","code":"BRL","symbol":"R$","position":0},{"title":"britainga pound sterling","code":"GBP","symbol":"£","position":0},{"title":"bruneiga dollar","code":"BND","symbol":"$","position":0},{"title":"burundiga franc","code":"BIF","symbol":"","position":0},{"title":"danemarkga krone","code":"DKK","symbol":"kr","position":0},{"title":"dominicaga peso","code":"DOP","symbol":"RD$","position":0},{"title":"dzamaikaga dollar","code":"JMD","symbol":"J$","position":0},{"title":"dzapanga yen","code":"JPY","symbol":"¥","position":0},{"title":"dziboutiga franc","code":"DJF","symbol":"","position":0},{"title":"dziehe koreaga won","code":"KPW","symbol":"₩","position":0},{"title":"dzɔdziaga lari","code":"GEL","symbol":"","position":0},{"title":"egyptega pound","code":"EGP","symbol":"£","position":0},{"title":"eritreaga nakfa","code":"ERN","symbol":"","position":0},{"title":"ethiopiaga birr","code":"ETB","symbol":"","position":0},{"title":"euro","code":"EUR","symbol":"€","position":0},{"title":"falklanɖ ƒudomekpo dukɔwo ƒe ga pound","code":"FKP","symbol":"£","position":0},{"title":"fidziga dollar","code":"FJD","symbol":"$","position":0},{"title":"filipiniga peso","code":"PHP","symbol":"P","position":0},{"title":"gambiaga dalasi","code":"GMD","symbol":"","position":0},{"title":"ghana siɖi","code":"GHS","symbol":"","position":0},{"title":"gilbrataga pound","code":"GIP","symbol":"£","position":0},{"title":"giniga franc","code":"GNF","symbol":"","position":0},{"title":"guatemalaga quetzal","code":"GTQ","symbol":"Q","position":0},{"title":"guyanaga dollar","code":"GYD","symbol":"$","position":0},{"title":"ɣedzeƒe caribbeaga dollar","code":"XCD","symbol":"$","position":0},{"title":"haitiga gourde","code":"HTG","symbol":"","position":0},{"title":"honduraga lempira","code":"HNL","symbol":"L","position":0},{"title":"hong kongga dollar","code":"HKD","symbol":"$","position":0},{"title":"hungariaga forint","code":"HUF","symbol":"Ft","position":0},{"title":"indiaga rupee","code":"INR","symbol":"","position":0},{"title":"indinesiaga rupiah","code":"IDR","symbol":"Rp","position":0},{"title":"irakga dinar","code":"IQD","symbol":"","position":0},{"title":"iranga rial","code":"IRR","symbol":"﷼","position":0},{"title":"israelga yeyetɔ sheqel","code":"ILS","symbol":"₪","position":0},{"title":"kambodiaga riel","code":"KHR","symbol":"៛","position":0},{"title":"kanadaga dollar","code":"CAD","symbol":"$","position":0},{"title":"kape verdega escudo","code":"CVE","symbol":"","position":0},{"title":"katarga rial","code":"QAR","symbol":"﷼","position":0},{"title":"kayman ƒudomekpoga dollar","code":"KYD","symbol":"$","position":0},{"title":"kazakhstanga tenge","code":"KZT","symbol":"лв","position":0},{"title":"kenyaga shilling","code":"KES","symbol":"","position":0},{"title":"kirgistanga som","code":"KGS","symbol":"лв","position":0},{"title":"kolombiaga peso","code":"COP","symbol":"$","position":0},{"title":"kolombiaga vavãtɔ","code":"COU","symbol":"","position":0},{"title":"komoroga franc","code":"KMF","symbol":"","position":0},{"title":"kongoga franc","code":"CDF","symbol":"","position":0},{"title":"kosta rikaga kolón","code":"CRC","symbol":"₡","position":0},{"title":"kubaga peso","code":"CUP","symbol":"₱","position":0},{"title":"kuwaitga dinar","code":"KWD","symbol":"","position":0},{"title":"laosga kip","code":"LAK","symbol":"₭","position":0},{"title":"lebanonga pound","code":"LBP","symbol":"£","position":0},{"title":"lesotoga loti","code":"LSL","symbol":"","position":0},{"title":"liberiaga dollar","code":"LRD","symbol":"$","position":0},{"title":"libyaga dinar","code":"LYD","symbol":"","position":0},{"title":"makanesega pataca","code":"MOP","symbol":"","position":0},{"title":"makedoniaga denar","code":"MKD","symbol":"ден","position":0},{"title":"malagasega ariary","code":"MGA","symbol":"","position":0},{"title":"Malawian Kwacha","code":"MWK","symbol":"","position":0},{"title":"malaysiaga ringit","code":"MYR","symbol":"RM","position":0},{"title":"maldiviaga rufiyaa","code":"MVR","symbol":"","position":0},{"title":"Mexican Investment Unit","code":"MXV","symbol":"","position":0},{"title":"meksikoga peso","code":"MXN","symbol":"$","position":0},{"title":"moldovaga leu","code":"MDL","symbol":"","position":0},{"title":"mongoliaga tugrik","code":"MNT","symbol":"₮","position":0},{"title":"morokoga dirham","code":"MAD","symbol":"","position":0},{"title":"Mozambican Metical","code":"MZN","symbol":"MT","position":0},{"title":"mɔritiusga rupee","code":"MUR","symbol":"₨","position":0},{"title":"myanmaga kyat","code":"MMK","symbol":"","position":0},{"title":"naidzeriaga naira","code":"NGN","symbol":"₦","position":0},{"title":"Namibian Dollar","code":"NAD","symbol":"$","position":0},{"title":"nedalands antilleaga guilder","code":"ANG","symbol":"ƒ","position":0},{"title":"nepalga rupee","code":"NPR","symbol":"₨","position":0},{"title":"new zealanɖga dollar","code":"NZD","symbol":"$","position":0},{"title":"nikaraguaga córdoba","code":"NIO","symbol":"C$","position":0},{"title":"norwayga krone","code":"NOK","symbol":"kr","position":0},{"title":"omanga rial","code":"OMR","symbol":"﷼","position":0},{"title":"pakistaniga rupee","code":"PKR","symbol":"₨","position":0},{"title":"panamaga balboa","code":"PAB","symbol":"B/.","position":0},{"title":"papua new guineaga kina","code":"PGK","symbol":"","position":0},{"title":"paraguayga guarani","code":"PYG","symbol":"Gs","position":0},{"title":"peruga nuevo sol","code":"PEN","symbol":"S/.","position":0},{"title":"polanɖga zloty","code":"PLN","symbol":"zł","position":0},{"title":"romaniaga leu","code":"RON","symbol":"lei","position":0},{"title":"rɔtsiaga ruble","code":"RUB","symbol":"руб","position":0},{"title":"rwandaga franc","code":"RWF","symbol":"","position":0},{"title":"saint helenaga pound","code":"SHP","symbol":"£","position":0},{"title":"samaoga tala","code":"WST","symbol":"","position":0},{"title":"saudiga riyal","code":"SAR","symbol":"﷼","position":0},{"title":"serbiaga dinar","code":"RSD","symbol":"Дин","position":0},{"title":"sɛtselsga rupee","code":"SCR","symbol":"₨","position":0},{"title":"singapɔga dollar","code":"SGD","symbol":"$","position":0},{"title":"solomon ƒudomekpo dukɔwo ƒe ga dollar","code":"SBD","symbol":"$","position":0},{"title":"somaliaga shilling","code":"SOS","symbol":"S","position":0},{"title":"South Sudanese Pound","code":"SSP","symbol":"","position":0},{"title":"sri lankaga rupee","code":"LKR","symbol":"₨","position":0},{"title":"sudanga pound","code":"SDG","symbol":"","position":0},{"title":"surinamga dollar","code":"SRD","symbol":"$","position":0},{"title":"swaziga lilangeni","code":"SZL","symbol":"","position":0},{"title":"swedenga krona","code":"SEK","symbol":"kr","position":0},{"title":"swissga franc","code":"CHF","symbol":"","position":0},{"title":"syriaga pound","code":"SYP","symbol":"£","position":0},{"title":"taiwanga yeye dollar","code":"TWD","symbol":"NT$","position":0},{"title":"tajikistanga somoni","code":"TJS","symbol":"","position":0},{"title":"Tanzaniatɔwofɛgadudu","code":"TZS","symbol":"","position":0},{"title":"tɛkiiga lira","code":"TRY","symbol":"","position":0},{"title":"thaiga baht","code":"THB","symbol":"฿","position":0},{"title":"tonagaga pa’anga","code":"TOP","symbol":"","position":0},{"title":"trinidad kple tobagoga dollar","code":"TTD","symbol":"TT$","position":0},{"title":"tunisiaga dinar","code":"TND","symbol":"","position":0},{"title":"turkmenistanga manat","code":"TMT","symbol":"","position":0},{"title":"tsainaga yuan","code":"CNY","symbol":"¥","position":0},{"title":"tsɛk repɔblikga koruna","code":"CZK","symbol":"Kč","position":0},{"title":"tsilega peso","code":"CLP","symbol":"$","position":0},{"title":"tsilegakɔnta dzidzenu UF","code":"CLF","symbol":"","position":0},{"title":"ugandaga shilling","code":"UGX","symbol":"","position":0},{"title":"ukrainega hryvnia","code":"UAH","symbol":"₴","position":0},{"title":"united arab emiratesga dirham","code":"AED","symbol":"","position":0},{"title":"uruguayga peso","code":"UYU","symbol":"$U","position":0},{"title":"us ga dollar","code":"USD","symbol":"$","position":0},{"title":"uzbekistanga som","code":"UZS","symbol":"лв","position":0},{"title":"vanuatuga vatu","code":"VUV","symbol":"","position":0},{"title":"vietnamga dong","code":"VND","symbol":"₫","position":0},{"title":"yemeniga rial","code":"YER","symbol":"﷼","position":0},{"title":"yɔdanga dinar","code":"JOD","symbol":"","position":0},{"title":"zambiaga kwacha","code":"ZMW","symbol":"","position":0}]