<?xml version="1.0" encoding="utf-8"?>
<currencies language="ne"><currency><title><![CDATA[Belarusian Ruble]]></title><code>BYN</code><symbol>Br</symbol><position>0</position></currency><currency><title><![CDATA[Bolivian Mvdol]]></title><code>BOV</code><symbol/><position>0</position></currency><currency><title><![CDATA[Chilean Unit of Account (UF)]]></title><code>CLF</code><symbol/><position>0</position></currency><currency><title><![CDATA[Colombian Real Value Unit]]></title><code>COU</code><symbol/><position>0</position></currency><currency><title><![CDATA[Lesotho Loti]]></title><code>LSL</code><symbol/><position>0</position></currency><currency><title><![CDATA[Mauritanian Ouguiya]]></title><code>MRU</code><symbol>UM</symbol><position>0</position></currency><currency><title><![CDATA[Mexican Investment Unit]]></title><code>MXV</code><symbol/><position>0</position></currency><currency><title><![CDATA[Sierra Leonean Leone]]></title><code>SLE</code><symbol>Le</symbol><position>0</position></currency><currency><title><![CDATA[São Tomé & Príncipe Dobra]]></title><code>STN</code><symbol>Db</symbol><position>0</position></currency><currency><title><![CDATA[Venezuelan Bolívar Soberano]]></title><code>VES</code><symbol>Bs.S</symbol><position>0</position></currency><currency><title><![CDATA[Zimbabwe Gold]]></title><code>ZWG</code><symbol>ZiG</symbol><position>0</position></currency><currency><title><![CDATA[अजरबैजानी मानात]]></title><code>AZN</code><symbol>ман</symbol><position>0</position></currency><currency><title><![CDATA[अफ्गान अफ्गानी]]></title><code>AFN</code><symbol>؋</symbol><position>0</position></currency><currency><title><![CDATA[अमेरिकी डलर]]></title><code>USD</code><symbol>$</symbol><position>0</position></currency><currency><title><![CDATA[अर्जेन्टिनी पेसो]]></title><code>ARS</code><symbol>$</symbol><position>0</position></currency><currency><title><![CDATA[अल्जेरियाली डिनार]]></title><code>DZD</code><symbol/><position>0</position></currency><currency><title><![CDATA[अल्बानियन लेक]]></title><code>ALL</code><symbol>Lek</symbol><position>0</position></currency><currency><title><![CDATA[अष्ट्रेलियन डलर]]></title><code>AUD</code><symbol>$</symbol><position>0</position></currency><currency><title><![CDATA[आइसल्याण्डिक क्रोना]]></title><code>ISK</code><symbol>kr</symbol><position>0</position></currency><currency><title><![CDATA[आरूबन फ्लोरिन]]></title><code>AWG</code><symbol>ƒ</symbol><position>0</position></currency><currency><title><![CDATA[आर्मेनियाली ड्राम]]></title><code>AMD</code><symbol/><position>0</position></currency><currency><title><![CDATA[इजरायली नयाँ शेकेल]]></title><code>ILS</code><symbol>₪</symbol><position>0</position></currency><currency><title><![CDATA[इजिप्सियन पाउन्ड]]></title><code>EGP</code><symbol>£</symbol><position>0</position></currency><currency><title><![CDATA[इण्डोनेशियाली रूपियाँ]]></title><code>IDR</code><symbol>Rp</symbol><position>0</position></currency><currency><title><![CDATA[इथियोपियाली बिर]]></title><code>ETB</code><symbol/><position>0</position></currency><currency><title><![CDATA[इराकी डिनार]]></title><code>IQD</code><symbol/><position>0</position></currency><currency><title><![CDATA[इरानियाली रियाल]]></title><code>IRR</code><symbol>﷼</symbol><position>0</position></currency><currency><title><![CDATA[उज्बेकिस्तान सोम]]></title><code>UZS</code><symbol>лв</symbol><position>0</position></currency><currency><title><![CDATA[उत्तर कोरियाली वन]]></title><code>KPW</code><symbol>₩</symbol><position>0</position></currency><currency><title><![CDATA[उरूगुवायाली पेसो]]></title><code>UYU</code><symbol>$U</symbol><position>0</position></currency><currency><title><![CDATA[एङ्गोलान क्वान्जा]]></title><code>AOA</code><symbol/><position>0</position></currency><currency><title><![CDATA[एरिट्रियन नाक्फा]]></title><code>ERN</code><symbol/><position>0</position></currency><currency><title><![CDATA[ओमनी रियल]]></title><code>OMR</code><symbol>﷼</symbol><position>0</position></currency><currency><title><![CDATA[कङ्गोली फ्रान्क]]></title><code>CDF</code><symbol/><position>0</position></currency><currency><title><![CDATA[कतारी रियल]]></title><code>QAR</code><symbol>﷼</symbol><position>0</position></currency><currency><title><![CDATA[कम्बोडिनेयाली रियल]]></title><code>KHR</code><symbol>៛</symbol><position>0</position></currency><currency><title><![CDATA[काजाखस्तानी टेन्ज]]></title><code>KZT</code><symbol>лв</symbol><position>0</position></currency><currency><title><![CDATA[किर्गिस्तानी सोम]]></title><code>KGS</code><symbol>лв</symbol><position>0</position></currency><currency><title><![CDATA[कुवेती डिनार]]></title><code>KWD</code><symbol/><position>0</position></currency><currency><title><![CDATA[केन्याली शिलिङ]]></title><code>KES</code><symbol/><position>0</position></currency><currency><title><![CDATA[केप भर्डियन एस्कुडो]]></title><code>CVE</code><symbol/><position>0</position></currency><currency><title><![CDATA[केम्यान टापुहरूका डलर]]></title><code>KYD</code><symbol>$</symbol><position>0</position></currency><currency><title><![CDATA[कोमोरियन फ्रान्क]]></title><code>KMF</code><symbol/><position>0</position></currency><currency><title><![CDATA[कोलम्वियन पेसो]]></title><code>COP</code><symbol>$</symbol><position>0</position></currency><currency><title><![CDATA[कोष्टारिकन कोलोन]]></title><code>CRC</code><symbol>₡</symbol><position>0</position></currency><currency><title><![CDATA[क्यानाडियाली डलर]]></title><code>CAD</code><symbol>$</symbol><position>0</position></currency><currency><title><![CDATA[क्यूवाली पेसो]]></title><code>CUP</code><symbol>₱</symbol><position>0</position></currency><currency><title><![CDATA[गाइनिज डलर]]></title><code>GYD</code><symbol>$</symbol><position>0</position></currency><currency><title><![CDATA[गाम्वियाली डालासी]]></title><code>GMD</code><symbol/><position>0</position></currency><currency><title><![CDATA[गिनियाली फ्रान्क]]></title><code>GNF</code><symbol/><position>0</position></currency><currency><title><![CDATA[ग्वाटेमाला क्वेट्जाल]]></title><code>GTQ</code><symbol>Q</symbol><position>0</position></currency><currency><title><![CDATA[घानाली सेडी]]></title><code>GHS</code><symbol/><position>0</position></currency><currency><title><![CDATA[चिनिँया युआन]]></title><code>CNY</code><symbol>¥</symbol><position>0</position></currency><currency><title><![CDATA[चिलियन पेसो]]></title><code>CLP</code><symbol>$</symbol><position>0</position></currency><currency><title><![CDATA[चेख गणतञ्त्र कोरूना]]></title><code>CZK</code><symbol>Kč</symbol><position>0</position></currency><currency><title><![CDATA[जमाइकाली डलर]]></title><code>JMD</code><symbol>J$</symbol><position>0</position></currency><currency><title><![CDATA[जर्जियाली लारी]]></title><code>GEL</code><symbol/><position>0</position></currency><currency><title><![CDATA[जापानी येन]]></title><code>JPY</code><symbol>¥</symbol><position>0</position></currency><currency><title><![CDATA[जाम्बियाली क्वाचा]]></title><code>ZMW</code><symbol/><position>0</position></currency><currency><title><![CDATA[जिबौंटियाली फ्रान्क]]></title><code>DJF</code><symbol/><position>0</position></currency><currency><title><![CDATA[जिब्राल्टर पाउण्ड]]></title><code>GIP</code><symbol>£</symbol><position>0</position></currency><currency><title><![CDATA[जोर्डानियाली डलर]]></title><code>JOD</code><symbol/><position>0</position></currency><currency><title><![CDATA[टङ्गन पाङ्गा]]></title><code>TOP</code><symbol/><position>0</position></currency><currency><title><![CDATA[टर्किश लिरा]]></title><code>TRY</code><symbol/><position>0</position></currency><currency><title><![CDATA[टुनिसियाली डिनार]]></title><code>TND</code><symbol/><position>0</position></currency><currency><title><![CDATA[टुर्क्मेनिस्तानी मानात]]></title><code>TMT</code><symbol/><position>0</position></currency><currency><title><![CDATA[डोमिनिकन पेसो]]></title><code>DOP</code><symbol>RD$</symbol><position>0</position></currency><currency><title><![CDATA[ड्यानिश क्रोन]]></title><code>DKK</code><symbol>kr</symbol><position>0</position></currency><currency><title><![CDATA[ताजिक्स्तानी सोमोनी]]></title><code>TJS</code><symbol/><position>0</position></currency><currency><title><![CDATA[ताञ्जानियाली शिलिङ]]></title><code>TZS</code><symbol/><position>0</position></currency><currency><title><![CDATA[त्रिनिडाड र टोबागो डलर]]></title><code>TTD</code><symbol>TT$</symbol><position>0</position></currency><currency><title><![CDATA[थाई भाट]]></title><code>THB</code><symbol>฿</symbol><position>0</position></currency><currency><title><![CDATA[दक्षिण अफ्रिकी र्‍यान्ड]]></title><code>ZAR</code><symbol>R</symbol><position>0</position></currency><currency><title><![CDATA[दक्षिण कोरियाली वन]]></title><code>KRW</code><symbol>₩</symbol><position>0</position></currency><currency><title><![CDATA[दक्षिण सुडानी पाउन्ड]]></title><code>SSP</code><symbol/><position>0</position></currency><currency><title><![CDATA[नयाँ ताइवान डलर]]></title><code>TWD</code><symbol>NT$</symbol><position>0</position></currency><currency><title><![CDATA[नर्वेजियाली क्रोन]]></title><code>NOK</code><symbol>kr</symbol><position>0</position></currency><currency><title><![CDATA[नाइजेरियन नाइरा]]></title><code>NGN</code><symbol>₦</symbol><position>0</position></currency><currency><title><![CDATA[नामिबियन डलर]]></title><code>NAD</code><symbol>$</symbol><position>0</position></currency><currency><title><![CDATA[निकारागुवान कोर्डोवा]]></title><code>NIO</code><symbol>C$</symbol><position>0</position></currency><currency><title><![CDATA[नेदरल्याण्ड्स एन्टिलियन गिल्डर]]></title><code>ANG</code><symbol>ƒ</symbol><position>0</position></currency><currency><title><![CDATA[नेपाली रूपैयाँ]]></title><code>NPR</code><symbol>₨</symbol><position>0</position></currency><currency><title><![CDATA[न्यूजिल्याण्ड डलर]]></title><code>NZD</code><symbol>$</symbol><position>0</position></currency><currency><title><![CDATA[पपुआ न्यू गिनियाली किना]]></title><code>PGK</code><symbol/><position>0</position></currency><currency><title><![CDATA[पाकिस्तानी रूपियाँ]]></title><code>PKR</code><symbol>₨</symbol><position>0</position></currency><currency><title><![CDATA[पानामानियाली बाल्बोआ]]></title><code>PAB</code><symbol>B/.</symbol><position>0</position></currency><currency><title><![CDATA[पारागुयाली गुरानी]]></title><code>PYG</code><symbol>Gs</symbol><position>0</position></currency><currency><title><![CDATA[पूर्वी क्यारिबियन डलर]]></title><code>XCD</code><symbol>$</symbol><position>0</position></currency><currency><title><![CDATA[पेरूभियाली न्यूभो सोल]]></title><code>PEN</code><symbol>S/.</symbol><position>0</position></currency><currency><title><![CDATA[पोलिश ज्लोटाई]]></title><code>PLN</code><symbol>zł</symbol><position>0</position></currency><currency><title><![CDATA[फक्‌ल्याण्ड टापुहरूका पाउन्ड]]></title><code>FKP</code><symbol>£</symbol><position>0</position></currency><currency><title><![CDATA[फिजीयाली डलर]]></title><code>FJD</code><symbol>$</symbol><position>0</position></currency><currency><title><![CDATA[फिलिपिनी पेसो]]></title><code>PHP</code><symbol>P</symbol><position>0</position></currency><currency><title><![CDATA[बङ्गलादेशी टाका]]></title><code>BDT</code><symbol/><position>0</position></currency><currency><title><![CDATA[बर्बाडियन डलर]]></title><code>BBD</code><symbol>$</symbol><position>0</position></currency><currency><title><![CDATA[बर्मुडन डलर]]></title><code>BMD</code><symbol>$</symbol><position>0</position></currency><currency><title><![CDATA[बहामियाली डलर]]></title><code>BSD</code><symbol>$</symbol><position>0</position></currency><currency><title><![CDATA[बाहारैनी डिनार]]></title><code>BHD</code><symbol/><position>0</position></currency><currency><title><![CDATA[बुरूण्डियाली फ्रान्क]]></title><code>BIF</code><symbol/><position>0</position></currency><currency><title><![CDATA[बेलायती पाउण्ड स्टर्लिङ]]></title><code>GBP</code><symbol>£</symbol><position>0</position></currency><currency><title><![CDATA[बोट्सवानान पुला]]></title><code>BWP</code><symbol>P</symbol><position>0</position></currency><currency><title><![CDATA[बोलिभियन बोलिभियानो]]></title><code>BOB</code><symbol>$b</symbol><position>0</position></currency><currency><title><![CDATA[बोस्निया-हर्जगोभिनिया रूपान्तरयोग्य मार्क]]></title><code>BAM</code><symbol>KM</symbol><position>0</position></currency><currency><title><![CDATA[ब्राजिलियन रियल]]></title><code>BRL</code><symbol>R$</symbol><position>0</position></currency><currency><title><![CDATA[ब्रुनाई डलर]]></title><code>BND</code><symbol>$</symbol><position>0</position></currency><currency><title><![CDATA[भानुआतू भातु]]></title><code>VUV</code><symbol/><position>0</position></currency><currency><title><![CDATA[भारती रूपिँया]]></title><code>INR</code><symbol/><position>0</position></currency><currency><title><![CDATA[भियतनामी डङ्]]></title><code>VND</code><symbol>₫</symbol><position>0</position></currency><currency><title><![CDATA[भुटानी एन्‌गुल्ट्रुम]]></title><code>BTN</code><symbol/><position>0</position></currency><currency><title><![CDATA[मङ्गोलियाली टुग्रिक]]></title><code>MNT</code><symbol>₮</symbol><position>0</position></currency><currency><title><![CDATA[मलाविअन क्वाचा]]></title><code>MWK</code><symbol/><position>0</position></currency><currency><title><![CDATA[मलेशियाली रिङ्गेट]]></title><code>MYR</code><symbol>RM</symbol><position>0</position></currency><currency><title><![CDATA[माउरिटियन रूपी]]></title><code>MUR</code><symbol>₨</symbol><position>0</position></currency><currency><title><![CDATA[माकानिज पटाका]]></title><code>MOP</code><symbol/><position>0</position></currency><currency><title><![CDATA[मालडिभियाली रूफियाँ]]></title><code>MVR</code><symbol/><position>0</position></currency><currency><title><![CDATA[मालागासी एरिआरी]]></title><code>MGA</code><symbol/><position>0</position></currency><currency><title><![CDATA[माल्डोभन लेउ]]></title><code>MDL</code><symbol/><position>0</position></currency><currency><title><![CDATA[मेक्सिकन पेसो]]></title><code>MXN</code><symbol>$</symbol><position>0</position></currency><currency><title><![CDATA[मोजाम्विकन मेटिकल]]></title><code>MZN</code><symbol>MT</symbol><position>0</position></currency><currency><title><![CDATA[मोरोक्काली डिर्‌हाम]]></title><code>MAD</code><symbol/><position>0</position></currency><currency><title><![CDATA[म्यान्मा क्याट]]></title><code>MMK</code><symbol/><position>0</position></currency><currency><title><![CDATA[म्यासेडोनियाली डेनार]]></title><code>MKD</code><symbol>ден</symbol><position>0</position></currency><currency><title><![CDATA[युक्रेनी हिर्भिनिया]]></title><code>UAH</code><symbol>₴</symbol><position>0</position></currency><currency><title><![CDATA[युगाण्डाली शिलिङ]]></title><code>UGX</code><symbol/><position>0</position></currency><currency><title><![CDATA[युरो]]></title><code>EUR</code><symbol>€</symbol><position>0</position></currency><currency><title><![CDATA[येमेनी रियाल]]></title><code>YER</code><symbol>﷼</symbol><position>0</position></currency><currency><title><![CDATA[रूसी रूबल]]></title><code>RUB</code><symbol>руб</symbol><position>0</position></currency><currency><title><![CDATA[रोमानियाली लेऊ]]></title><code>RON</code><symbol>lei</symbol><position>0</position></currency><currency><title><![CDATA[र्‌वाण्डाली फ्रान्क]]></title><code>RWF</code><symbol/><position>0</position></currency><currency><title><![CDATA[लाओशियन किप]]></title><code>LAK</code><symbol>₭</symbol><position>0</position></currency><currency><title><![CDATA[लिबेरियाली डलर]]></title><code>LRD</code><symbol>$</symbol><position>0</position></currency><currency><title><![CDATA[लिवियाली डिनार]]></title><code>LYD</code><symbol/><position>0</position></currency><currency><title><![CDATA[लेबनाली पाउन्ड]]></title><code>LBP</code><symbol>£</symbol><position>0</position></currency><currency><title><![CDATA[वेलिज डलर]]></title><code>BZD</code><symbol>BZ$</symbol><position>0</position></currency><currency><title><![CDATA[श्रीलङ्काली रूपिया]]></title><code>LKR</code><symbol>₨</symbol><position>0</position></currency><currency><title><![CDATA[संयुक्त अरब एमिराट्स डिर्हाम]]></title><code>AED</code><symbol/><position>0</position></currency><currency><title><![CDATA[सर्बियाली डिनार]]></title><code>RSD</code><symbol>Дин</symbol><position>0</position></currency><currency><title><![CDATA[साउदी रियालहरू]]></title><code>SAR</code><symbol>﷼</symbol><position>0</position></currency><currency><title><![CDATA[सामोआन ताला]]></title><code>WST</code><symbol/><position>0</position></currency><currency><title><![CDATA[सिङ्गापुर डलर]]></title><code>SGD</code><symbol>$</symbol><position>0</position></currency><currency><title><![CDATA[सिरियाली पाउन्ड]]></title><code>SYP</code><symbol>£</symbol><position>0</position></currency><currency><title><![CDATA[सुडानी पाउन्ड]]></title><code>SDG</code><symbol/><position>0</position></currency><currency><title><![CDATA[सुरिनामिज डलर]]></title><code>SRD</code><symbol>$</symbol><position>0</position></currency><currency><title><![CDATA[सेचेलोइस रूपी]]></title><code>SCR</code><symbol>₨</symbol><position>0</position></currency><currency><title><![CDATA[सेन्ट हेलेना पाउन्ड]]></title><code>SHP</code><symbol>£</symbol><position>0</position></currency><currency><title><![CDATA[सोमाली शिलिङ]]></title><code>SOS</code><symbol>S</symbol><position>0</position></currency><currency><title><![CDATA[सोलोमन टापुहरूका डलर]]></title><code>SBD</code><symbol>$</symbol><position>0</position></currency><currency><title><![CDATA[स्वाजी लिलान्गेनी]]></title><code>SZL</code><symbol/><position>0</position></currency><currency><title><![CDATA[स्विडिश क्रोना]]></title><code>SEK</code><symbol>kr</symbol><position>0</position></currency><currency><title><![CDATA[स्विस् फ्रैङ्क]]></title><code>CHF</code><symbol/><position>0</position></currency><currency><title><![CDATA[हङकङ डलर]]></title><code>HKD</code><symbol>$</symbol><position>0</position></currency><currency><title><![CDATA[हङ्गेरियन फोरिन्ट]]></title><code>HUF</code><symbol>Ft</symbol><position>0</position></currency><currency><title><![CDATA[हैटियाली गुर्ड]]></title><code>HTG</code><symbol/><position>0</position></currency><currency><title><![CDATA[होन्डुरान लेम्पिरा]]></title><code>HNL</code><symbol>L</symbol><position>0</position></currency></currencies>
