[{"title":"بِلیروشِیَن رِبٕل","code":"BYN","symbol":"Br","position":0},{"title":"Cape Verdean Escudo","code":"CVE","symbol":"","position":0},{"title":"Djiboutian Franc","code":"DJF","symbol":"","position":0},{"title":"مورِٹینِیَن عوگیوٗیا","code":"MRU","symbol":"UM","position":0},{"title":"Mexican Investment Unit","code":"MXV","symbol":"","position":0},{"title":"Seychellois Rupee","code":"SCR","symbol":"₨","position":0},{"title":"Sierra Leonean Leone","code":"SLE","symbol":"Le","position":0},{"title":"South Sudanese Pound","code":"SSP","symbol":"","position":0},{"title":"São Tomé & Príncipe Dobra","code":"STN","symbol":"Db","position":0},{"title":"Turkmenistani Manat","code":"TMT","symbol":"","position":0},{"title":"وینٕزوٗلیُک بولِوَر","code":"VES","symbol":"Bs.S","position":0},{"title":"Zimbabwean Gold","code":"ZWG","symbol":"ZiG","position":0},{"title":"آزَرباجانی مَنَٹ","code":"AZN","symbol":"ман","position":0},{"title":"آسٹریلِیَن ڈالَر","code":"AUD","symbol":"$","position":0},{"title":"أرجَنٹیٖن پِسو","code":"ARS","symbol":"$","position":0},{"title":"اٮ۪لبینِیَن لِک","code":"ALL","symbol":"Lek","position":0},{"title":"اٮ۪لجیرِیَن ڈیٖنار","code":"DZD","symbol":"","position":0},{"title":"اٮ۪نگولَن کوانزا","code":"AOA","symbol":"","position":0},{"title":"اُبیکِستان سوم","code":"UZS","symbol":"лв","position":0},{"title":"اِتھوپِیَن بِر","code":"ETB","symbol":"","position":0},{"title":"اِجِپٹِیَن پَوُنڑ","code":"EGP","symbol":"£","position":0},{"title":"اَرمانٮ۪ن ڈرٛٮ۪م","code":"AMD","symbol":"","position":0},{"title":"اَروبَن فِلورِن","code":"AWG","symbol":"ƒ","position":0},{"title":"اُروٗگایَن پیٚسو","code":"UYU","symbol":"$U","position":0},{"title":"اِزرٲیِلی نٔوۍ شٮ۪قٕل","code":"ILS","symbol":"₪","position":0},{"title":"افغان افغٲنی","code":"AFN","symbol":"؋","position":0},{"title":"اُگاداہُک شِلِنٛگ","code":"UGX","symbol":"","position":0},{"title":"اِنڑونیشیاہُک رُپِیاہ","code":"IDR","symbol":"Rp","position":0},{"title":"اومِنی رِیال","code":"OMR","symbol":"﷼","position":0},{"title":"ایٖراقُک دیٖنار","code":"IQD","symbol":"","position":0},{"title":"ایٖرانُک رِیال","code":"IRR","symbol":"﷼","position":0},{"title":"اَیسلینٛڑُک کرٛونا","code":"ISK","symbol":"kr","position":0},{"title":"بابیڑِیَن ڈالَر","code":"BBD","symbol":"$","position":0},{"title":"بحریٖنی دیٖنار","code":"BHD","symbol":"","position":0},{"title":"برٛازیٖلین رِیَل","code":"BRL","symbol":"R$","position":0},{"title":"برطٲنوی پاونٛڑ سٹٔرلِنٛگ","code":"GBP","symbol":"£","position":0},{"title":"بٔرمیوٗڑَن ڈالَر","code":"BMD","symbol":"$","position":0},{"title":"بُرُنڑِین فرینٛک","code":"BIF","symbol":"","position":0},{"title":"برٛونی ڈالَر","code":"BND","symbol":"$","position":0},{"title":"بِلِزی ڈالر","code":"BZD","symbol":"BZ$","position":0},{"title":"بَنگلادیٖشی ٹَکا","code":"BDT","symbol":"","position":0},{"title":"بہامِیَن ڈالر","code":"BSD","symbol":"$","position":0},{"title":"بوٹٕسوانَن پُلا","code":"BWP","symbol":"P","position":0},{"title":"بوٗٹینیٖز نگُلٹرٛم","code":"BTN","symbol":"","position":0},{"title":"بوزنِیاہَرزِگووِنا کَنوٲٹیبٕل مارٕک","code":"BAM","symbol":"KM","position":0},{"title":"بولِوِیَن بولوینو","code":"BOB","symbol":"$b","position":0},{"title":"بولوِیَن مَوڈال","code":"BOV","symbol":"","position":0},{"title":"پاکِستٲنۍ رۄپَے","code":"PKR","symbol":"₨","position":0},{"title":"پانامانِیَن بالبوز","code":"PAB","symbol":"B/.","position":0},{"title":"پٮ۪رٮ۪گیوٗوَیَن گُعارانی","code":"PYG","symbol":"Gs","position":0},{"title":"پٔریوٗوِیَن نیوٗاوز سولٕز","code":"PEN","symbol":"S/.","position":0},{"title":"پھِلِپایِٔن پٮ۪سو","code":"PHP","symbol":"P","position":0},{"title":"پولِش زلوٹی","code":"PLN","symbol":"zł","position":0},{"title":"تاجِکتانُک سَمونی","code":"TJS","symbol":"","position":0},{"title":"تُرکیہُک لیرا","code":"TRY","symbol":"","position":0},{"title":"تَنزانیاہُک شِلِنٛگ","code":"TZS","symbol":"","position":0},{"title":"تھایھک بات","code":"THB","symbol":"฿","position":0},{"title":"ٹرِنہِ ڈیڈ تہٕ ٹوبیگو ڈالَر","code":"TTD","symbol":"TT$","position":0},{"title":"ٹُنیشیاہُک دیٖنار","code":"TND","symbol":"","position":0},{"title":"ٹونگَن پانٛگا","code":"TOP","symbol":"","position":0},{"title":"جاپانُک یَن","code":"JPY","symbol":"¥","position":0},{"title":"جارجِیَن لاری","code":"GEL","symbol":"","position":0},{"title":"جَرڑینیاہُک دیٖنار","code":"JOD","symbol":"","position":0},{"title":"جَمَیکاہُک ڑالَر","code":"JMD","symbol":"J$","position":0},{"title":"جنوٗبی کورِیَن وَن","code":"KPW","symbol":"₩","position":0},{"title":"چِلِن پِسو","code":"CLP","symbol":"$","position":0},{"title":"چِلِن یوٗنِڑیدیٖز ڑِ فومیٹو","code":"CLF","symbol":"","position":0},{"title":"چیک کوریٖنا","code":"CZK","symbol":"Kč","position":0},{"title":"چینیٖز یَن رِنمِنبی","code":"CNY","symbol":"¥","position":0},{"title":"حانٛگ کانٛگُک ڑالَر","code":"HKD","symbol":"$","position":0},{"title":"حَنگیرِیَن فورِنٛٹ","code":"HUF","symbol":"Ft","position":0},{"title":"حونڑورنُک لٮ۪مپیٖرا","code":"HNL","symbol":"L","position":0},{"title":"حیشَنُک گوڑ","code":"HTG","symbol":"","position":0},{"title":"ڈٔنِش کرٛون","code":"DKK","symbol":"kr","position":0},{"title":"ڈومِنِکَن پِسو","code":"DOP","symbol":"RD$","position":0},{"title":"رِٹریٖن نَفکا","code":"ERN","symbol":"","position":0},{"title":"رٔشیَن رَبٕل","code":"RUB","symbol":"руб","position":0},{"title":"روانٛڑَن فرانٛک","code":"RWF","symbol":"","position":0},{"title":"رومانِیَن لٮ۪یوٗ","code":"RON","symbol":"lei","position":0},{"title":"زِمبابیُک کواچا","code":"ZMW","symbol":"","position":0},{"title":"ساوُتھ افریٖکاہُک رینڈ","code":"ZAR","symbol":"R","position":0},{"title":"ساوتھ کورِیَن وَن","code":"KRW","symbol":"₩","position":0},{"title":"سٔربِیَن دیٖنار","code":"RSD","symbol":"Дин","position":0},{"title":"سری لَنکاہٕچ رۄپَے","code":"LKR","symbol":"₨","position":0},{"title":"سُریٖنامُک ڈالَر","code":"SRD","symbol":"$","position":0},{"title":"سَمون تَلا","code":"WST","symbol":"","position":0},{"title":"سِنگاپورُک ڈالَر","code":"SGD","symbol":"$","position":0},{"title":"سوازی لِلَنگیٚنی","code":"SZL","symbol":"","position":0},{"title":"سودیٖیُک رِیال","code":"SAR","symbol":"﷼","position":0},{"title":"سوٗڈانُک پونٛڈ","code":"SDG","symbol":"","position":0},{"title":"سُوِز فریک","code":"CHF","symbol":"","position":0},{"title":"سولَمَن جٔزیٖرُک ڈالَر","code":"SBD","symbol":"$","position":0},{"title":"سومالی شِلِنٛگ","code":"SOS","symbol":"S","position":0},{"title":"سویٖڈِش کَرونا","code":"SEK","symbol":"kr","position":0},{"title":"سیٖریاہُک پونٛڈ","code":"SYP","symbol":"£","position":0},{"title":"سینٹ ہیلِنا پونٛڈ","code":"SHP","symbol":"£","position":0},{"title":"فِجین ڈالر","code":"FJD","symbol":"$","position":0},{"title":"فیکلینٛڑِس آیلینٛڑ پونٛڑ","code":"FKP","symbol":"£","position":0},{"title":"قطاری رِیال","code":"QAR","symbol":"﷼","position":0},{"title":"قُویتُک دیٖنار","code":"KWD","symbol":"","position":0},{"title":"کٮ۪نیَن شِلِنٛگ","code":"KES","symbol":"","position":0},{"title":"کِرگِستانُک سوم","code":"KGS","symbol":"лв","position":0},{"title":"کزاکِستان ٹینٛج","code":"KZT","symbol":"лв","position":0},{"title":"کَمبوڑِیاہُک رِیال","code":"KHR","symbol":"៛","position":0},{"title":"کوسٹا رِکَن کولَن","code":"CRC","symbol":"₡","position":0},{"title":"کولَمبِین پِسو","code":"COP","symbol":"$","position":0},{"title":"کومورِیَن فرٛینٛک","code":"KMF","symbol":"","position":0},{"title":"کونٛگولیٖز فرٛیک","code":"CDF","symbol":"","position":0},{"title":"کیمین ججیٖرُک ڑالَر","code":"KYD","symbol":"$","position":0},{"title":"کینَڑِیَن ڈالر","code":"CAD","symbol":"$","position":0},{"title":"کیوٗبَن پِسو","code":"CUP","symbol":"₱","position":0},{"title":"گِبریلٹَر پَاونٛڑ","code":"GIP","symbol":"£","position":0},{"title":"گِنِیَن فرٛینٛک","code":"GNF","symbol":"","position":0},{"title":"گَنیٚیَن سٮ۪ڑی","code":"GHS","symbol":"","position":0},{"title":"گواٹَمالَن قیوٗٹزَل","code":"GTQ","symbol":"Q","position":0},{"title":"گیمبِیاہُک دلاسی","code":"GMD","symbol":"","position":0},{"title":"گَیَنیٖزُک ڑالَر","code":"GYD","symbol":"$","position":0},{"title":"لِبیَن دیٖنار","code":"LYD","symbol":"","position":0},{"title":"لِسوتھو لوٹی","code":"LSL","symbol":"","position":0},{"title":"لَوٹِیَن کِپ","code":"LAK","symbol":"₭","position":0},{"title":"لیبنیٖزُک پاونٛڑ","code":"LBP","symbol":"£","position":0},{"title":"لَیبیرِیَن ڑالَر","code":"LRD","symbol":"$","position":0},{"title":"مالدِیٖوِیَن رُفِیا","code":"MVR","symbol":"","position":0},{"title":"مٮ۪کانیٖز پَٹاکا","code":"MOP","symbol":"","position":0},{"title":"مٮ۪کَڑونِیَن دیٖنار","code":"MKD","symbol":"ден","position":0},{"title":"مٮ۪کسِکَن پٮ۪سو","code":"MXN","symbol":"$","position":0},{"title":"مٮ۪لٮ۪گیسی اٮ۪ریَری","code":"MGA","symbol":"","position":0},{"title":"مٮ۪لیوِیَن کواچا","code":"MWK","symbol":"","position":0},{"title":"مُتحدہ عرب اِمارات دِرہم","code":"AED","symbol":"","position":0},{"title":"مَشرِقی کیرِبِیَن ڈالَر","code":"XCD","symbol":"$","position":0},{"title":"مَلیشِیَن رِنٛگِٹ","code":"MYR","symbol":"RM","position":0},{"title":"مورٮ۪شِیاہٕچ رۄپَے","code":"MUR","symbol":"₨","position":0},{"title":"موروکَن دِرہَم","code":"MAD","symbol":"","position":0},{"title":"موزیمبِکَن مٮ۪ٹِکَل","code":"MZN","symbol":"MT","position":0},{"title":"مولڑووین لیوٗ","code":"MDL","symbol":"","position":0},{"title":"مۄنگولِیَن ٹُگرِک","code":"MNT","symbol":"₮","position":0},{"title":"مِیانما کیاٹ","code":"MMK","symbol":"","position":0},{"title":"نامِبِیَن ڑالَر","code":"NAD","symbol":"$","position":0},{"title":"نایدَرلینٛڑ اٮ۪نٹٕلیٖیَن گِلڑَر","code":"ANG","symbol":"ƒ","position":0},{"title":"نِکٮ۪راگُوٮ۪ن کورڑوبا اورو","code":"NIO","symbol":"C$","position":0},{"title":"نورویٚیِنُک کرٛون","code":"NOK","symbol":"kr","position":0},{"title":"نِوزیٖلینٛڑُک ڑالَر","code":"NZD","symbol":"$","position":0},{"title":"نوٚو تیوانُک ڈالَر","code":"TWD","symbol":"NT$","position":0},{"title":"نیپالٕچ رۄپَے","code":"NPR","symbol":"₨","position":0},{"title":"نَیجیرِیَن ڑالَر","code":"NGN","symbol":"₦","position":0},{"title":"نیوٗ پیپُعا گِنِیَن کیٖنا","code":"PGK","symbol":"","position":0},{"title":"ہِندُستٲنۍ رۄپَے","code":"INR","symbol":"","position":0},{"title":"وَنوٗاَتوٗ وَتوٗ","code":"VUV","symbol":"","position":0},{"title":"وِیَنَمُک ڈانٛگ","code":"VND","symbol":"₫","position":0},{"title":"یَمنُک رِیال","code":"YER","symbol":"﷼","position":0},{"title":"یوٗ ایٚس ڈالَر","code":"USD","symbol":"$","position":0},{"title":"یوٗرو","code":"EUR","symbol":"€","position":0},{"title":"یوٗکرینیاہُک ہرِوِنیا","code":"UAH","symbol":"₴","position":0},{"title":"ِٖیوٗنِڑیڑ ڑِ ویلور رِیل","code":"COU","symbol":"","position":0}]